package j.a.b.m;

public class b
  implements n<Object>
{
  /* Error */
  public <E> void a(E paramE, Appendable paramAppendable, j.a.b.g paramg)
  {
    // Byte code:
    //   0: aload_1
    //   1: invokevirtual 20	java/lang/Object:getClass	()Ljava/lang/Class;
    //   4: getstatic 25	j/a/b/h:a	Lj/a/b/h$a;
    //   7: invokestatic 30	j/a/a/c:a	(Ljava/lang/Class;Lj/a/a/i;)Lj/a/a/c;
    //   10: astore 4
    //   12: aload_2
    //   13: bipush 123
    //   15: invokeinterface 36 2 0
    //   20: pop
    //   21: aload 4
    //   23: invokevirtual 39	j/a/a/c:a	()[Lj/a/a/a;
    //   26: astore 5
    //   28: aload 5
    //   30: arraylength
    //   31: istore 6
    //   33: iconst_0
    //   34: istore 7
    //   36: iconst_0
    //   37: istore 8
    //   39: iload 7
    //   41: iload 6
    //   43: if_icmplt +13 -> 56
    //   46: aload_2
    //   47: bipush 125
    //   49: invokeinterface 36 2 0
    //   54: pop
    //   55: return
    //   56: aload 5
    //   58: iload 7
    //   60: aaload
    //   61: astore 9
    //   63: aload 4
    //   65: aload_1
    //   66: aload 9
    //   68: getfield 45	j/a/a/a:d	I
    //   71: invokevirtual 48	j/a/a/c:a	(Ljava/lang/Object;I)Ljava/lang/Object;
    //   74: astore 10
    //   76: aload 10
    //   78: ifnonnull +13 -> 91
    //   81: aload_3
    //   82: getfield 53	j/a/b/g:d	Z
    //   85: ifeq +6 -> 91
    //   88: goto +35 -> 123
    //   91: iload 8
    //   93: ifeq +15 -> 108
    //   96: aload_2
    //   97: bipush 44
    //   99: invokeinterface 36 2 0
    //   104: pop
    //   105: goto +6 -> 111
    //   108: iconst_1
    //   109: istore 8
    //   111: aload 9
    //   113: getfield 57	j/a/a/a:f	Ljava/lang/String;
    //   116: aload 10
    //   118: aload_2
    //   119: aload_3
    //   120: invokestatic 62	j/a/b/d:a	(Ljava/lang/String;Ljava/lang/Object;Ljava/lang/Appendable;Lj/a/b/g;)V
    //   123: iinc 7 1
    //   126: goto -87 -> 39
    //   129: astore_1
    //   130: aload_1
    //   131: athrow
    // Local variable table:
    //   start	length	slot	name	signature
    //   0	132	0	this	b
    //   0	132	1	paramE	E
    //   0	132	2	paramAppendable	Appendable
    //   0	132	3	paramg	j.a.b.g
    //   10	54	4	localc	j.a.a.c
    //   26	31	5	arrayOfa	j.a.a.a[]
    //   31	13	6	i	int
    //   34	90	7	j	int
    //   37	73	8	k	int
    //   61	51	9	locala	j.a.a.a
    //   74	43	10	localObject	Object
    // Exception table:
    //   from	to	target	type
    //   0	33	129	java/io/IOException
    //   46	55	129	java/io/IOException
    //   63	76	129	java/io/IOException
    //   81	88	129	java/io/IOException
    //   96	105	129	java/io/IOException
    //   111	123	129	java/io/IOException
  }
}

/* Location:
 * Qualified Name:     j.a.b.m.b
 * Java Class Version: 6 (50.0)
 * JD-Core Version:    0.7.1
 */