package i.a.b;

public class j$a
  implements j.g
{
  /* Error */
  public void a(String paramString, Appendable paramAppendable)
  {
    // Byte code:
    //   0: aload_1
    //   1: invokevirtual 24	java/lang/String:length	()I
    //   4: istore_3
    //   5: iconst_0
    //   6: istore 4
    //   8: iload 4
    //   10: iload_3
    //   11: if_icmplt +4 -> 15
    //   14: return
    //   15: aload_1
    //   16: iload 4
    //   18: invokevirtual 28	java/lang/String:charAt	(I)C
    //   21: istore 5
    //   23: iload 5
    //   25: bipush 12
    //   27: if_icmpeq +290 -> 317
    //   30: iload 5
    //   32: bipush 13
    //   34: if_icmpeq +271 -> 305
    //   37: iload 5
    //   39: bipush 34
    //   41: if_icmpeq +252 -> 293
    //   44: iload 5
    //   46: bipush 47
    //   48: if_icmpeq +233 -> 281
    //   51: iload 5
    //   53: bipush 92
    //   55: if_icmpeq +214 -> 269
    //   58: iload 5
    //   60: tableswitch	default:+28->88, 8:+197->257, 9:+185->245, 10:+173->233
    //   88: iload 5
    //   90: iflt +10 -> 100
    //   93: iload 5
    //   95: bipush 31
    //   97: if_icmple +34 -> 131
    //   100: iload 5
    //   102: bipush 127
    //   104: if_icmplt +11 -> 115
    //   107: iload 5
    //   109: sipush 159
    //   112: if_icmple +19 -> 131
    //   115: iload 5
    //   117: sipush 8192
    //   120: if_icmplt +101 -> 221
    //   123: iload 5
    //   125: sipush 8447
    //   128: if_icmpgt +93 -> 221
    //   131: aload_2
    //   132: ldc 30
    //   134: invokeinterface 36 2 0
    //   139: pop
    //   140: aload_2
    //   141: ldc 38
    //   143: iload 5
    //   145: bipush 12
    //   147: ishr
    //   148: bipush 15
    //   150: iand
    //   151: invokevirtual 28	java/lang/String:charAt	(I)C
    //   154: invokeinterface 41 2 0
    //   159: pop
    //   160: aload_2
    //   161: ldc 38
    //   163: iload 5
    //   165: bipush 8
    //   167: ishr
    //   168: bipush 15
    //   170: iand
    //   171: invokevirtual 28	java/lang/String:charAt	(I)C
    //   174: invokeinterface 41 2 0
    //   179: pop
    //   180: aload_2
    //   181: ldc 38
    //   183: iload 5
    //   185: iconst_4
    //   186: ishr
    //   187: bipush 15
    //   189: iand
    //   190: invokevirtual 28	java/lang/String:charAt	(I)C
    //   193: invokeinterface 41 2 0
    //   198: pop
    //   199: aload_2
    //   200: ldc 38
    //   202: iload 5
    //   204: iconst_0
    //   205: ishr
    //   206: bipush 15
    //   208: iand
    //   209: invokevirtual 28	java/lang/String:charAt	(I)C
    //   212: invokeinterface 41 2 0
    //   217: pop
    //   218: goto +108 -> 326
    //   221: aload_2
    //   222: iload 5
    //   224: invokeinterface 41 2 0
    //   229: pop
    //   230: goto +96 -> 326
    //   233: aload_2
    //   234: ldc 43
    //   236: invokeinterface 36 2 0
    //   241: pop
    //   242: goto +84 -> 326
    //   245: aload_2
    //   246: ldc 45
    //   248: invokeinterface 36 2 0
    //   253: pop
    //   254: goto +72 -> 326
    //   257: aload_2
    //   258: ldc 47
    //   260: invokeinterface 36 2 0
    //   265: pop
    //   266: goto +60 -> 326
    //   269: aload_2
    //   270: ldc 49
    //   272: invokeinterface 36 2 0
    //   277: pop
    //   278: goto +48 -> 326
    //   281: aload_2
    //   282: ldc 51
    //   284: invokeinterface 36 2 0
    //   289: pop
    //   290: goto +36 -> 326
    //   293: aload_2
    //   294: ldc 53
    //   296: invokeinterface 36 2 0
    //   301: pop
    //   302: goto +24 -> 326
    //   305: aload_2
    //   306: ldc 55
    //   308: invokeinterface 36 2 0
    //   313: pop
    //   314: goto +12 -> 326
    //   317: aload_2
    //   318: ldc 57
    //   320: invokeinterface 36 2 0
    //   325: pop
    //   326: iinc 4 1
    //   329: goto -321 -> 8
    //   332: astore_1
    //   333: new 59	java/lang/RuntimeException
    //   336: dup
    //   337: ldc 61
    //   339: invokespecial 64	java/lang/RuntimeException:<init>	(Ljava/lang/String;)V
    //   342: athrow
    // Local variable table:
    //   start	length	slot	name	signature
    //   0	343	0	this	a
    //   0	343	1	paramString	String
    //   0	343	2	paramAppendable	Appendable
    //   4	8	3	i	int
    //   6	321	4	j	int
    //   21	202	5	c	char
    // Exception table:
    //   from	to	target	type
    //   0	5	332	java/io/IOException
    //   15	23	332	java/io/IOException
    //   131	218	332	java/io/IOException
    //   221	230	332	java/io/IOException
    //   233	242	332	java/io/IOException
    //   245	254	332	java/io/IOException
    //   257	266	332	java/io/IOException
    //   269	278	332	java/io/IOException
    //   281	290	332	java/io/IOException
    //   293	302	332	java/io/IOException
    //   305	314	332	java/io/IOException
    //   317	326	332	java/io/IOException
  }
}

/* Location:
 * Qualified Name:     base.i.a.b.j.a
 * Java Class Version: 6 (50.0)
 * JD-Core Version:    0.7.1
 */