package l.d.a;

import java.util.concurrent.ExecutorService;

public final class b
  implements Runnable, l
{
  public final k x;
  public final c y;
  public volatile boolean z;
  
  public b(c paramc)
  {
    y = paramc;
    x = new k();
  }
  
  public void a(q paramq, Object paramObject)
  {
    paramq = j.a(paramq, paramObject);
    try
    {
      x.a(paramq);
      if (!z)
      {
        z = true;
        y.j.execute(this);
      }
      return;
    }
    finally {}
  }
  
  /* Error */
  public void run()
  {
    // Byte code:
    //   0: aload_0
    //   1: getfield 26	l/d/a/b:x	Ll/d/a/k;
    //   4: sipush 1000
    //   7: invokevirtual 57	l/d/a/k:a	(I)Ll/d/a/j;
    //   10: astore_1
    //   11: aload_1
    //   12: astore_2
    //   13: aload_1
    //   14: ifnonnull +40 -> 54
    //   17: aload_0
    //   18: monitorenter
    //   19: aload_0
    //   20: getfield 26	l/d/a/b:x	Ll/d/a/k;
    //   23: invokevirtual 60	l/d/a/k:a	()Ll/d/a/j;
    //   26: astore_2
    //   27: aload_2
    //   28: ifnonnull +16 -> 44
    //   31: aload_0
    //   32: iconst_0
    //   33: putfield 39	l/d/a/b:z	Z
    //   36: aload_0
    //   37: monitorexit
    //   38: aload_0
    //   39: iconst_0
    //   40: putfield 39	l/d/a/b:z	Z
    //   43: return
    //   44: aload_0
    //   45: monitorexit
    //   46: goto +8 -> 54
    //   49: astore_2
    //   50: aload_0
    //   51: monitorexit
    //   52: aload_2
    //   53: athrow
    //   54: aload_0
    //   55: getfield 21	l/d/a/b:y	Ll/d/a/c;
    //   58: aload_2
    //   59: invokevirtual 61	l/d/a/c:a	(Ll/d/a/j;)V
    //   62: goto -62 -> 0
    //   65: astore_2
    //   66: goto +65 -> 131
    //   69: astore_3
    //   70: aload_0
    //   71: getfield 21	l/d/a/b:y	Ll/d/a/c;
    //   74: getfield 65	l/d/a/c:r	Ll/d/a/g;
    //   77: astore_1
    //   78: getstatic 71	java/util/logging/Level:WARNING	Ljava/util/logging/Level;
    //   81: astore_2
    //   82: new 73	java/lang/StringBuilder
    //   85: astore 4
    //   87: aload 4
    //   89: invokespecial 74	java/lang/StringBuilder:<init>	()V
    //   92: aload 4
    //   94: invokestatic 80	java/lang/Thread:currentThread	()Ljava/lang/Thread;
    //   97: invokevirtual 84	java/lang/Thread:getName	()Ljava/lang/String;
    //   100: invokevirtual 88	java/lang/StringBuilder:append	(Ljava/lang/String;)Ljava/lang/StringBuilder;
    //   103: pop
    //   104: aload 4
    //   106: ldc 90
    //   108: invokevirtual 88	java/lang/StringBuilder:append	(Ljava/lang/String;)Ljava/lang/StringBuilder;
    //   111: pop
    //   112: aload_1
    //   113: aload_2
    //   114: aload 4
    //   116: invokevirtual 93	java/lang/StringBuilder:toString	()Ljava/lang/String;
    //   119: aload_3
    //   120: invokeinterface 98 4 0
    //   125: aload_0
    //   126: iconst_0
    //   127: putfield 39	l/d/a/b:z	Z
    //   130: return
    //   131: aload_0
    //   132: iconst_0
    //   133: putfield 39	l/d/a/b:z	Z
    //   136: aload_2
    //   137: athrow
    // Local variable table:
    //   start	length	slot	name	signature
    //   0	138	0	this	b
    //   10	103	1	localObject1	Object
    //   12	16	2	localObject2	Object
    //   49	10	2	localj	j
    //   65	1	2	localObject3	Object
    //   81	56	2	localLevel	java.util.logging.Level
    //   69	51	3	localInterruptedException	InterruptedException
    //   85	30	4	localStringBuilder	StringBuilder
    // Exception table:
    //   from	to	target	type
    //   19	27	49	finally
    //   31	38	49	finally
    //   44	46	49	finally
    //   50	52	49	finally
    //   0	11	65	finally
    //   17	19	65	finally
    //   52	54	65	finally
    //   54	62	65	finally
    //   70	125	65	finally
    //   0	11	69	java/lang/InterruptedException
    //   17	19	69	java/lang/InterruptedException
    //   52	54	69	java/lang/InterruptedException
    //   54	62	69	java/lang/InterruptedException
  }
}

/* Location:
 * Qualified Name:     l.d.a.b
 * Java Class Version: 6 (50.0)
 * JD-Core Version:    0.7.1
 */