package l.c.a.a.a.s;

import java.util.concurrent.ExecutorService;
import l.c.a.a.a.f;
import l.c.a.a.a.q;
import l.c.a.a.a.s.s.e;

public class a$b
  implements Runnable
{
  public String A;
  public e x;
  public long y;
  public q z;
  
  public a$b(a parama, e parame, long paramLong, q paramq)
  {
    x = parame;
    y = paramLong;
    z = paramq;
  }
  
  public void a()
  {
    Object localObject = new StringBuilder("MQTT Disc: ");
    ((StringBuilder)localObject).append(B.c).y);
    A = ((StringBuilder)localObject).toString();
    localObject = B.r;
    if (localObject == null) {
      new Thread(this).start();
    } else {
      ((ExecutorService)localObject).execute(this);
    }
  }
  
  /* Error */
  public void run()
  {
    // Byte code:
    //   0: invokestatic 83	java/lang/Thread:currentThread	()Ljava/lang/Thread;
    //   3: aload_0
    //   4: getfield 59	l/c/a/a/a/s/a$b:A	Ljava/lang/String;
    //   7: invokevirtual 86	java/lang/Thread:setName	(Ljava/lang/String;)V
    //   10: aload_0
    //   11: getfield 23	l/c/a/a/a/s/a$b:B	Ll/c/a/a/a/s/a;
    //   14: astore_1
    //   15: aload_1
    //   16: getfield 89	l/c/a/a/a/s/a:b	Ll/c/a/a/a/t/b;
    //   19: aload_1
    //   20: getfield 91	l/c/a/a/a/s/a:a	Ljava/lang/String;
    //   23: ldc 93
    //   25: ldc 95
    //   27: invokeinterface 100 4 0
    //   32: aload_0
    //   33: getfield 23	l/c/a/a/a/s/a$b:B	Ll/c/a/a/a/s/a;
    //   36: getfield 104	l/c/a/a/a/s/a:i	Ll/c/a/a/a/s/b;
    //   39: aload_0
    //   40: getfield 30	l/c/a/a/a/s/a$b:y	J
    //   43: invokevirtual 109	l/c/a/a/a/s/b:a	(J)V
    //   46: aload_0
    //   47: getfield 23	l/c/a/a/a/s/a$b:B	Ll/c/a/a/a/s/a;
    //   50: aload_0
    //   51: getfield 28	l/c/a/a/a/s/a$b:x	Ll/c/a/a/a/s/s/e;
    //   54: aload_0
    //   55: getfield 32	l/c/a/a/a/s/a$b:z	Ll/c/a/a/a/q;
    //   58: invokevirtual 112	l/c/a/a/a/s/a:a	(Ll/c/a/a/a/s/s/u;Ll/c/a/a/a/q;)V
    //   61: aload_0
    //   62: getfield 23	l/c/a/a/a/s/a$b:B	Ll/c/a/a/a/s/a;
    //   65: getfield 116	l/c/a/a/a/s/a:g	Ll/c/a/a/a/s/e;
    //   68: ifnull +26 -> 94
    //   71: aload_0
    //   72: getfield 23	l/c/a/a/a/s/a$b:B	Ll/c/a/a/a/s/a;
    //   75: getfield 116	l/c/a/a/a/s/a:g	Ll/c/a/a/a/s/e;
    //   78: invokevirtual 121	l/c/a/a/a/s/e:a	()Z
    //   81: ifeq +13 -> 94
    //   84: aload_0
    //   85: getfield 32	l/c/a/a/a/s/a$b:z	Ll/c/a/a/a/q;
    //   88: getfield 126	l/c/a/a/a/q:a	Ll/c/a/a/a/s/p;
    //   91: invokevirtual 130	l/c/a/a/a/s/p:c	()V
    //   94: aload_0
    //   95: getfield 32	l/c/a/a/a/s/a$b:z	Ll/c/a/a/a/q;
    //   98: getfield 126	l/c/a/a/a/q:a	Ll/c/a/a/a/s/p;
    //   101: aconst_null
    //   102: aconst_null
    //   103: invokevirtual 133	l/c/a/a/a/s/p:a	(Ll/c/a/a/a/s/s/u;Ll/c/a/a/a/k;)V
    //   106: aload_0
    //   107: getfield 23	l/c/a/a/a/s/a$b:B	Ll/c/a/a/a/s/a;
    //   110: getfield 116	l/c/a/a/a/s/a:g	Ll/c/a/a/a/s/e;
    //   113: astore_1
    //   114: aload_1
    //   115: ifnull +101 -> 216
    //   118: aload_1
    //   119: invokevirtual 121	l/c/a/a/a/s/e:a	()Z
    //   122: ifne +104 -> 226
    //   125: goto +91 -> 216
    //   128: astore_1
    //   129: aload_0
    //   130: getfield 32	l/c/a/a/a/s/a$b:z	Ll/c/a/a/a/q;
    //   133: getfield 126	l/c/a/a/a/q:a	Ll/c/a/a/a/s/p;
    //   136: aconst_null
    //   137: aconst_null
    //   138: invokevirtual 133	l/c/a/a/a/s/p:a	(Ll/c/a/a/a/s/s/u;Ll/c/a/a/a/k;)V
    //   141: aload_0
    //   142: getfield 23	l/c/a/a/a/s/a$b:B	Ll/c/a/a/a/s/a;
    //   145: getfield 116	l/c/a/a/a/s/a:g	Ll/c/a/a/a/s/e;
    //   148: astore_2
    //   149: aload_2
    //   150: ifnull +10 -> 160
    //   153: aload_2
    //   154: invokevirtual 121	l/c/a/a/a/s/e:a	()Z
    //   157: ifne +13 -> 170
    //   160: aload_0
    //   161: getfield 32	l/c/a/a/a/s/a$b:z	Ll/c/a/a/a/q;
    //   164: getfield 126	l/c/a/a/a/q:a	Ll/c/a/a/a/s/p;
    //   167: invokevirtual 135	l/c/a/a/a/s/p:a	()V
    //   170: aload_0
    //   171: getfield 23	l/c/a/a/a/s/a$b:B	Ll/c/a/a/a/s/a;
    //   174: aload_0
    //   175: getfield 32	l/c/a/a/a/s/a$b:z	Ll/c/a/a/a/q;
    //   178: aconst_null
    //   179: invokevirtual 138	l/c/a/a/a/s/a:a	(Ll/c/a/a/a/q;Ll/c/a/a/a/k;)V
    //   182: aload_1
    //   183: athrow
    //   184: astore_1
    //   185: aload_0
    //   186: getfield 32	l/c/a/a/a/s/a$b:z	Ll/c/a/a/a/q;
    //   189: getfield 126	l/c/a/a/a/q:a	Ll/c/a/a/a/s/p;
    //   192: aconst_null
    //   193: aconst_null
    //   194: invokevirtual 133	l/c/a/a/a/s/p:a	(Ll/c/a/a/a/s/s/u;Ll/c/a/a/a/k;)V
    //   197: aload_0
    //   198: getfield 23	l/c/a/a/a/s/a$b:B	Ll/c/a/a/a/s/a;
    //   201: getfield 116	l/c/a/a/a/s/a:g	Ll/c/a/a/a/s/e;
    //   204: astore_1
    //   205: aload_1
    //   206: ifnull +10 -> 216
    //   209: aload_1
    //   210: invokevirtual 121	l/c/a/a/a/s/e:a	()Z
    //   213: ifne +13 -> 226
    //   216: aload_0
    //   217: getfield 32	l/c/a/a/a/s/a$b:z	Ll/c/a/a/a/q;
    //   220: getfield 126	l/c/a/a/a/q:a	Ll/c/a/a/a/s/p;
    //   223: invokevirtual 135	l/c/a/a/a/s/p:a	()V
    //   226: aload_0
    //   227: getfield 23	l/c/a/a/a/s/a$b:B	Ll/c/a/a/a/s/a;
    //   230: aload_0
    //   231: getfield 32	l/c/a/a/a/s/a$b:z	Ll/c/a/a/a/q;
    //   234: aconst_null
    //   235: invokevirtual 138	l/c/a/a/a/s/a:a	(Ll/c/a/a/a/q;Ll/c/a/a/a/k;)V
    //   238: return
    // Local variable table:
    //   start	length	slot	name	signature
    //   0	239	0	this	b
    //   14	105	1	localObject1	Object
    //   128	55	1	localObject2	Object
    //   184	1	1	localk	l.c.a.a.a.k
    //   204	6	1	locale1	e
    //   148	6	2	locale2	e
    // Exception table:
    //   from	to	target	type
    //   46	94	128	finally
    //   46	94	184	l/c/a/a/a/k
  }
}

/* Location:
 * Qualified Name:     l.c.a.a.a.s.a.b
 * Java Class Version: 6 (50.0)
 * JD-Core Version:    0.7.1
 */