package l.c.a.a.a.s;

import java.io.InputStream;
import java.util.concurrent.ExecutorService;
import java.util.concurrent.Future;
import l.c.a.a.a.t.c;

public class d
  implements Runnable
{
  public static final String I = d.class.getName();
  public final Object A;
  public String B;
  public Future<?> C;
  public b D;
  public a E;
  public l.c.a.a.a.s.s.f F;
  public f G;
  public Thread H;
  public l.c.a.a.a.t.b x = c.a("org.eclipse.paho.client.mqttv3.internal.nls.logcat", I);
  public a y;
  public a z;
  
  public d(a parama, b paramb, f paramf, InputStream paramInputStream)
  {
    a locala = a.STOPPED;
    y = locala;
    z = locala;
    A = new Object();
    D = null;
    E = null;
    G = null;
    H = null;
    F = new l.c.a.a.a.s.s.f(paramb, paramInputStream);
    E = parama;
    D = paramb;
    G = paramf;
    x.a(c).y);
  }
  
  public void a(String arg1, ExecutorService paramExecutorService)
  {
    B = ???;
    x.b(I, "start", "855");
    synchronized (A)
    {
      if ((y == a.STOPPED) && (z == a.STOPPED))
      {
        z = a.RUNNING;
        if (paramExecutorService == null)
        {
          paramExecutorService = new java/lang/Thread;
          paramExecutorService.<init>(this);
          paramExecutorService.start();
        }
        else
        {
          C = paramExecutorService.submit(this);
        }
      }
      for (;;)
      {
        if (a()) {
          return;
        }
        try
        {
          Thread.sleep(100L);
        }
        catch (Exception ???) {}
      }
    }
  }
  
  public boolean a()
  {
    synchronized (A)
    {
      boolean bool;
      if (((y == a.RUNNING) || (y == a.RECEIVING)) && (z == a.RUNNING)) {
        bool = true;
      } else {
        bool = false;
      }
      return bool;
    }
  }
  
  public void b()
  {
    synchronized (A)
    {
      if (C != null) {
        C.cancel(true);
      }
      x.b(I, "stop", "850");
      if (a()) {
        z = a.STOPPED;
      }
      for (;;)
      {
        if (!a())
        {
          x.b(I, "stop", "851");
          return;
        }
        try
        {
          Thread.sleep(100L);
        }
        catch (Exception localException) {}
      }
    }
  }
  
  /* Error */
  public void run()
  {
    // Byte code:
    //   0: invokestatic 159	java/lang/Thread:currentThread	()Ljava/lang/Thread;
    //   3: astore_1
    //   4: aload_0
    //   5: aload_1
    //   6: putfield 73	l/c/a/a/a/s/d:H	Ljava/lang/Thread;
    //   9: aload_1
    //   10: aload_0
    //   11: getfield 100	l/c/a/a/a/s/d:B	Ljava/lang/String;
    //   14: invokevirtual 162	java/lang/Thread:setName	(Ljava/lang/String;)V
    //   17: aload_0
    //   18: getfield 65	l/c/a/a/a/s/d:A	Ljava/lang/Object;
    //   21: astore_1
    //   22: aload_1
    //   23: monitorenter
    //   24: aload_0
    //   25: getstatic 111	l/c/a/a/a/s/d$a:RUNNING	Ll/c/a/a/a/s/d$a;
    //   28: putfield 61	l/c/a/a/a/s/d:y	Ll/c/a/a/a/s/d$a;
    //   31: aload_1
    //   32: monitorexit
    //   33: aload_0
    //   34: getfield 65	l/c/a/a/a/s/d:A	Ljava/lang/Object;
    //   37: astore_1
    //   38: aload_1
    //   39: monitorenter
    //   40: aload_0
    //   41: getfield 63	l/c/a/a/a/s/d:z	Ll/c/a/a/a/s/d$a;
    //   44: astore_2
    //   45: aload_1
    //   46: monitorexit
    //   47: aconst_null
    //   48: astore_1
    //   49: aload_2
    //   50: getstatic 111	l/c/a/a/a/s/d$a:RUNNING	Ll/c/a/a/a/s/d$a;
    //   53: if_acmpne +569 -> 622
    //   56: aload_0
    //   57: getfield 80	l/c/a/a/a/s/d:F	Ll/c/a/a/a/s/s/f;
    //   60: astore_2
    //   61: aload_2
    //   62: ifnonnull +6 -> 68
    //   65: goto +557 -> 622
    //   68: aload_1
    //   69: astore_2
    //   70: aload_1
    //   71: astore_3
    //   72: aload_0
    //   73: getfield 56	l/c/a/a/a/s/d:x	Ll/c/a/a/a/t/b;
    //   76: getstatic 42	l/c/a/a/a/s/d:I	Ljava/lang/String;
    //   79: ldc -93
    //   81: ldc -91
    //   83: invokeinterface 108 4 0
    //   88: aload_1
    //   89: astore_2
    //   90: aload_1
    //   91: astore_3
    //   92: aload_0
    //   93: getfield 80	l/c/a/a/a/s/d:F	Ll/c/a/a/a/s/s/f;
    //   96: invokevirtual 169	l/c/a/a/a/s/s/f:available	()I
    //   99: ifle +45 -> 144
    //   102: aload_1
    //   103: astore_2
    //   104: aload_1
    //   105: astore_3
    //   106: aload_0
    //   107: getfield 65	l/c/a/a/a/s/d:A	Ljava/lang/Object;
    //   110: astore 4
    //   112: aload_1
    //   113: astore_2
    //   114: aload_1
    //   115: astore_3
    //   116: aload 4
    //   118: monitorenter
    //   119: aload_0
    //   120: getstatic 138	l/c/a/a/a/s/d$a:RECEIVING	Ll/c/a/a/a/s/d$a;
    //   123: putfield 61	l/c/a/a/a/s/d:y	Ll/c/a/a/a/s/d$a;
    //   126: aload 4
    //   128: monitorexit
    //   129: goto +15 -> 144
    //   132: astore 5
    //   134: aload 4
    //   136: monitorexit
    //   137: aload_1
    //   138: astore_2
    //   139: aload_1
    //   140: astore_3
    //   141: aload 5
    //   143: athrow
    //   144: aload_1
    //   145: astore_2
    //   146: aload_1
    //   147: astore_3
    //   148: aload_0
    //   149: getfield 80	l/c/a/a/a/s/d:F	Ll/c/a/a/a/s/s/f;
    //   152: invokevirtual 172	l/c/a/a/a/s/s/f:b	()Ll/c/a/a/a/s/s/u;
    //   155: astore 4
    //   157: aload_1
    //   158: astore_2
    //   159: aload_1
    //   160: astore_3
    //   161: aload_0
    //   162: getfield 65	l/c/a/a/a/s/d:A	Ljava/lang/Object;
    //   165: astore 5
    //   167: aload_1
    //   168: astore_2
    //   169: aload_1
    //   170: astore_3
    //   171: aload 5
    //   173: monitorenter
    //   174: aload_0
    //   175: getstatic 111	l/c/a/a/a/s/d$a:RUNNING	Ll/c/a/a/a/s/d$a;
    //   178: putfield 61	l/c/a/a/a/s/d:y	Ll/c/a/a/a/s/d$a;
    //   181: aload 5
    //   183: monitorexit
    //   184: aload_1
    //   185: astore_2
    //   186: aload_1
    //   187: astore_3
    //   188: aload 4
    //   190: instanceof 174
    //   193: ifeq +148 -> 341
    //   196: aload_1
    //   197: astore_2
    //   198: aload_1
    //   199: astore_3
    //   200: aload_0
    //   201: getfield 71	l/c/a/a/a/s/d:G	Ll/c/a/a/a/s/f;
    //   204: aload 4
    //   206: invokevirtual 179	l/c/a/a/a/s/f:a	(Ll/c/a/a/a/s/s/u;)Ll/c/a/a/a/q;
    //   209: astore_1
    //   210: aload_1
    //   211: ifnull +39 -> 250
    //   214: aload_1
    //   215: astore_2
    //   216: aload_1
    //   217: astore_3
    //   218: aload_1
    //   219: monitorenter
    //   220: aload_0
    //   221: getfield 67	l/c/a/a/a/s/d:D	Ll/c/a/a/a/s/b;
    //   224: aload 4
    //   226: checkcast 174	l/c/a/a/a/s/s/b
    //   229: invokevirtual 184	l/c/a/a/a/s/b:a	(Ll/c/a/a/a/s/s/b;)V
    //   232: aload_1
    //   233: monitorexit
    //   234: aload_1
    //   235: astore_2
    //   236: goto +127 -> 363
    //   239: astore 4
    //   241: aload_1
    //   242: monitorexit
    //   243: aload_1
    //   244: astore_2
    //   245: aload_1
    //   246: astore_3
    //   247: aload 4
    //   249: athrow
    //   250: aload_1
    //   251: astore_2
    //   252: aload_1
    //   253: astore_3
    //   254: aload 4
    //   256: instanceof 186
    //   259: ifne +57 -> 316
    //   262: aload_1
    //   263: astore_2
    //   264: aload_1
    //   265: astore_3
    //   266: aload 4
    //   268: instanceof 188
    //   271: ifne +45 -> 316
    //   274: aload_1
    //   275: astore_2
    //   276: aload_1
    //   277: astore_3
    //   278: aload 4
    //   280: instanceof 190
    //   283: ifeq +6 -> 289
    //   286: goto +30 -> 316
    //   289: aload_1
    //   290: astore_2
    //   291: aload_1
    //   292: astore_3
    //   293: new 153	l/c/a/a/a/k
    //   296: astore 4
    //   298: aload_1
    //   299: astore_2
    //   300: aload_1
    //   301: astore_3
    //   302: aload 4
    //   304: bipush 6
    //   306: invokespecial 193	l/c/a/a/a/k:<init>	(I)V
    //   309: aload_1
    //   310: astore_2
    //   311: aload_1
    //   312: astore_3
    //   313: aload 4
    //   315: athrow
    //   316: aload_1
    //   317: astore_2
    //   318: aload_1
    //   319: astore_3
    //   320: aload_0
    //   321: getfield 56	l/c/a/a/a/s/d:x	Ll/c/a/a/a/t/b;
    //   324: getstatic 42	l/c/a/a/a/s/d:I	Ljava/lang/String;
    //   327: ldc -93
    //   329: ldc -61
    //   331: invokeinterface 108 4 0
    //   336: aload_1
    //   337: astore_2
    //   338: goto +25 -> 363
    //   341: aload_1
    //   342: astore_2
    //   343: aload 4
    //   345: ifnull +18 -> 363
    //   348: aload_1
    //   349: astore_2
    //   350: aload_1
    //   351: astore_3
    //   352: aload_0
    //   353: getfield 67	l/c/a/a/a/s/d:D	Ll/c/a/a/a/s/b;
    //   356: aload 4
    //   358: invokevirtual 199	l/c/a/a/a/s/b:e	(Ll/c/a/a/a/s/s/u;)V
    //   361: aload_1
    //   362: astore_2
    //   363: aload_0
    //   364: getfield 65	l/c/a/a/a/s/d:A	Ljava/lang/Object;
    //   367: astore_1
    //   368: aload_1
    //   369: monitorenter
    //   370: aload_0
    //   371: getstatic 111	l/c/a/a/a/s/d$a:RUNNING	Ll/c/a/a/a/s/d$a;
    //   374: putfield 61	l/c/a/a/a/s/d:y	Ll/c/a/a/a/s/d$a;
    //   377: aload_1
    //   378: monitorexit
    //   379: aload_2
    //   380: astore_1
    //   381: goto +186 -> 567
    //   384: astore_2
    //   385: aload_1
    //   386: monitorexit
    //   387: aload_2
    //   388: athrow
    //   389: astore 4
    //   391: aload 5
    //   393: monitorexit
    //   394: aload_1
    //   395: astore_2
    //   396: aload_1
    //   397: astore_3
    //   398: aload 4
    //   400: athrow
    //   401: astore_2
    //   402: goto +197 -> 599
    //   405: astore_1
    //   406: aload_0
    //   407: getfield 56	l/c/a/a/a/s/d:x	Ll/c/a/a/a/t/b;
    //   410: getstatic 42	l/c/a/a/a/s/d:I	Ljava/lang/String;
    //   413: ldc -93
    //   415: ldc -55
    //   417: invokeinterface 108 4 0
    //   422: aload_0
    //   423: getfield 65	l/c/a/a/a/s/d:A	Ljava/lang/Object;
    //   426: astore_3
    //   427: aload_3
    //   428: monitorenter
    //   429: aload_0
    //   430: getstatic 59	l/c/a/a/a/s/d$a:STOPPED	Ll/c/a/a/a/s/d$a;
    //   433: putfield 63	l/c/a/a/a/s/d:z	Ll/c/a/a/a/s/d$a;
    //   436: aload_3
    //   437: monitorexit
    //   438: aload_0
    //   439: getfield 69	l/c/a/a/a/s/d:E	Ll/c/a/a/a/s/a;
    //   442: invokevirtual 203	l/c/a/a/a/s/a:e	()Z
    //   445: ifne +29 -> 474
    //   448: aload_0
    //   449: getfield 69	l/c/a/a/a/s/d:E	Ll/c/a/a/a/s/a;
    //   452: astore_3
    //   453: new 153	l/c/a/a/a/k
    //   456: astore 4
    //   458: aload 4
    //   460: sipush 32109
    //   463: aload_1
    //   464: invokespecial 206	l/c/a/a/a/k:<init>	(ILjava/lang/Throwable;)V
    //   467: aload_3
    //   468: aload_2
    //   469: aload 4
    //   471: invokevirtual 209	l/c/a/a/a/s/a:a	(Ll/c/a/a/a/q;Ll/c/a/a/a/k;)V
    //   474: aload_0
    //   475: getfield 65	l/c/a/a/a/s/d:A	Ljava/lang/Object;
    //   478: astore_1
    //   479: aload_1
    //   480: monitorenter
    //   481: aload_0
    //   482: getstatic 111	l/c/a/a/a/s/d$a:RUNNING	Ll/c/a/a/a/s/d$a;
    //   485: putfield 61	l/c/a/a/a/s/d:y	Ll/c/a/a/a/s/d$a;
    //   488: aload_1
    //   489: monitorexit
    //   490: aload_2
    //   491: astore_1
    //   492: goto +75 -> 567
    //   495: astore_2
    //   496: aload_1
    //   497: monitorexit
    //   498: aload_2
    //   499: athrow
    //   500: astore_1
    //   501: aload_3
    //   502: monitorexit
    //   503: aload_1
    //   504: athrow
    //   505: astore_2
    //   506: aload_0
    //   507: getfield 56	l/c/a/a/a/s/d:x	Ll/c/a/a/a/t/b;
    //   510: getstatic 42	l/c/a/a/a/s/d:I	Ljava/lang/String;
    //   513: ldc -93
    //   515: ldc -45
    //   517: aconst_null
    //   518: aload_2
    //   519: invokeinterface 214 6 0
    //   524: aload_0
    //   525: getfield 65	l/c/a/a/a/s/d:A	Ljava/lang/Object;
    //   528: astore_1
    //   529: aload_1
    //   530: monitorenter
    //   531: aload_0
    //   532: getstatic 59	l/c/a/a/a/s/d$a:STOPPED	Ll/c/a/a/a/s/d$a;
    //   535: putfield 63	l/c/a/a/a/s/d:z	Ll/c/a/a/a/s/d$a;
    //   538: aload_1
    //   539: monitorexit
    //   540: aload_0
    //   541: getfield 69	l/c/a/a/a/s/d:E	Ll/c/a/a/a/s/a;
    //   544: aload_3
    //   545: aload_2
    //   546: invokevirtual 209	l/c/a/a/a/s/a:a	(Ll/c/a/a/a/q;Ll/c/a/a/a/k;)V
    //   549: aload_0
    //   550: getfield 65	l/c/a/a/a/s/d:A	Ljava/lang/Object;
    //   553: astore_1
    //   554: aload_1
    //   555: monitorenter
    //   556: aload_0
    //   557: getstatic 111	l/c/a/a/a/s/d$a:RUNNING	Ll/c/a/a/a/s/d$a;
    //   560: putfield 61	l/c/a/a/a/s/d:y	Ll/c/a/a/a/s/d$a;
    //   563: aload_1
    //   564: monitorexit
    //   565: aload_3
    //   566: astore_1
    //   567: aload_0
    //   568: getfield 65	l/c/a/a/a/s/d:A	Ljava/lang/Object;
    //   571: astore_3
    //   572: aload_3
    //   573: monitorenter
    //   574: aload_0
    //   575: getfield 63	l/c/a/a/a/s/d:z	Ll/c/a/a/a/s/d$a;
    //   578: astore_2
    //   579: aload_3
    //   580: monitorexit
    //   581: goto -532 -> 49
    //   584: astore_1
    //   585: aload_3
    //   586: monitorexit
    //   587: aload_1
    //   588: athrow
    //   589: astore_2
    //   590: aload_1
    //   591: monitorexit
    //   592: aload_2
    //   593: athrow
    //   594: astore_2
    //   595: aload_1
    //   596: monitorexit
    //   597: aload_2
    //   598: athrow
    //   599: aload_0
    //   600: getfield 65	l/c/a/a/a/s/d:A	Ljava/lang/Object;
    //   603: astore_1
    //   604: aload_1
    //   605: monitorenter
    //   606: aload_0
    //   607: getstatic 111	l/c/a/a/a/s/d$a:RUNNING	Ll/c/a/a/a/s/d$a;
    //   610: putfield 61	l/c/a/a/a/s/d:y	Ll/c/a/a/a/s/d$a;
    //   613: aload_1
    //   614: monitorexit
    //   615: aload_2
    //   616: athrow
    //   617: astore_2
    //   618: aload_1
    //   619: monitorexit
    //   620: aload_2
    //   621: athrow
    //   622: aload_0
    //   623: getfield 65	l/c/a/a/a/s/d:A	Ljava/lang/Object;
    //   626: astore_2
    //   627: aload_2
    //   628: monitorenter
    //   629: aload_0
    //   630: getstatic 59	l/c/a/a/a/s/d$a:STOPPED	Ll/c/a/a/a/s/d$a;
    //   633: putfield 61	l/c/a/a/a/s/d:y	Ll/c/a/a/a/s/d$a;
    //   636: aload_2
    //   637: monitorexit
    //   638: aload_0
    //   639: aconst_null
    //   640: putfield 73	l/c/a/a/a/s/d:H	Ljava/lang/Thread;
    //   643: aload_0
    //   644: getfield 56	l/c/a/a/a/s/d:x	Ll/c/a/a/a/t/b;
    //   647: getstatic 42	l/c/a/a/a/s/d:I	Ljava/lang/String;
    //   650: ldc -93
    //   652: ldc -40
    //   654: invokeinterface 108 4 0
    //   659: return
    //   660: astore_1
    //   661: aload_2
    //   662: monitorexit
    //   663: aload_1
    //   664: athrow
    //   665: astore_2
    //   666: aload_1
    //   667: monitorexit
    //   668: aload_2
    //   669: athrow
    //   670: astore_2
    //   671: aload_0
    //   672: getfield 65	l/c/a/a/a/s/d:A	Ljava/lang/Object;
    //   675: astore_1
    //   676: aload_1
    //   677: monitorenter
    //   678: aload_0
    //   679: getstatic 59	l/c/a/a/a/s/d$a:STOPPED	Ll/c/a/a/a/s/d$a;
    //   682: putfield 61	l/c/a/a/a/s/d:y	Ll/c/a/a/a/s/d$a;
    //   685: aload_1
    //   686: monitorexit
    //   687: aload_2
    //   688: athrow
    //   689: astore_2
    //   690: aload_1
    //   691: monitorexit
    //   692: aload_2
    //   693: athrow
    //   694: astore_2
    //   695: aload_1
    //   696: monitorexit
    //   697: aload_2
    //   698: athrow
    // Local variable table:
    //   start	length	slot	name	signature
    //   0	699	0	this	d
    //   405	59	1	localIOException	java.io.IOException
    //   500	4	1	localObject3	Object
    //   584	12	1	localObject5	Object
    //   660	7	1	localObject7	Object
    //   44	336	2	localObject9	Object
    //   384	4	2	localObject10	Object
    //   395	1	2	localObject11	Object
    //   401	90	2	localq	l.c.a.a.a.q
    //   495	4	2	localObject12	Object
    //   505	41	2	localk1	l.c.a.a.a.k
    //   578	1	2	locala	a
    //   589	4	2	localObject13	Object
    //   594	22	2	localObject14	Object
    //   617	4	2	localObject15	Object
    //   665	4	2	localObject17	Object
    //   670	18	2	localObject18	Object
    //   689	4	2	localObject19	Object
    //   694	4	2	localObject20	Object
    //   110	115	4	localObject22	Object
    //   239	40	4	localObject23	Object
    //   296	61	4	localk2	l.c.a.a.a.k
    //   389	10	4	localObject24	Object
    //   456	14	4	localk3	l.c.a.a.a.k
    //   132	10	5	localObject25	Object
    //   165	227	5	localObject26	Object
    // Exception table:
    //   from	to	target	type
    //   119	129	132	finally
    //   134	137	132	finally
    //   220	234	239	finally
    //   241	243	239	finally
    //   370	379	384	finally
    //   385	387	384	finally
    //   174	184	389	finally
    //   391	394	389	finally
    //   72	88	401	finally
    //   92	102	401	finally
    //   106	112	401	finally
    //   116	119	401	finally
    //   141	144	401	finally
    //   148	157	401	finally
    //   161	167	401	finally
    //   171	174	401	finally
    //   188	196	401	finally
    //   200	210	401	finally
    //   218	220	401	finally
    //   247	250	401	finally
    //   254	262	401	finally
    //   266	274	401	finally
    //   278	286	401	finally
    //   293	298	401	finally
    //   302	309	401	finally
    //   313	316	401	finally
    //   320	336	401	finally
    //   352	361	401	finally
    //   398	401	401	finally
    //   406	429	401	finally
    //   438	474	401	finally
    //   503	505	401	finally
    //   506	531	401	finally
    //   540	549	401	finally
    //   597	599	401	finally
    //   72	88	405	java/io/IOException
    //   92	102	405	java/io/IOException
    //   106	112	405	java/io/IOException
    //   116	119	405	java/io/IOException
    //   141	144	405	java/io/IOException
    //   148	157	405	java/io/IOException
    //   161	167	405	java/io/IOException
    //   171	174	405	java/io/IOException
    //   188	196	405	java/io/IOException
    //   200	210	405	java/io/IOException
    //   218	220	405	java/io/IOException
    //   247	250	405	java/io/IOException
    //   254	262	405	java/io/IOException
    //   266	274	405	java/io/IOException
    //   278	286	405	java/io/IOException
    //   293	298	405	java/io/IOException
    //   302	309	405	java/io/IOException
    //   313	316	405	java/io/IOException
    //   320	336	405	java/io/IOException
    //   352	361	405	java/io/IOException
    //   398	401	405	java/io/IOException
    //   481	490	495	finally
    //   496	498	495	finally
    //   429	438	500	finally
    //   501	503	500	finally
    //   72	88	505	l/c/a/a/a/k
    //   92	102	505	l/c/a/a/a/k
    //   106	112	505	l/c/a/a/a/k
    //   116	119	505	l/c/a/a/a/k
    //   141	144	505	l/c/a/a/a/k
    //   148	157	505	l/c/a/a/a/k
    //   161	167	505	l/c/a/a/a/k
    //   171	174	505	l/c/a/a/a/k
    //   188	196	505	l/c/a/a/a/k
    //   200	210	505	l/c/a/a/a/k
    //   218	220	505	l/c/a/a/a/k
    //   247	250	505	l/c/a/a/a/k
    //   254	262	505	l/c/a/a/a/k
    //   266	274	505	l/c/a/a/a/k
    //   278	286	505	l/c/a/a/a/k
    //   293	298	505	l/c/a/a/a/k
    //   302	309	505	l/c/a/a/a/k
    //   313	316	505	l/c/a/a/a/k
    //   320	336	505	l/c/a/a/a/k
    //   352	361	505	l/c/a/a/a/k
    //   398	401	505	l/c/a/a/a/k
    //   574	581	584	finally
    //   585	587	584	finally
    //   556	565	589	finally
    //   590	592	589	finally
    //   531	540	594	finally
    //   595	597	594	finally
    //   606	615	617	finally
    //   618	620	617	finally
    //   629	638	660	finally
    //   661	663	660	finally
    //   40	47	665	finally
    //   666	668	665	finally
    //   33	40	670	finally
    //   49	61	670	finally
    //   363	370	670	finally
    //   387	389	670	finally
    //   474	481	670	finally
    //   498	500	670	finally
    //   549	556	670	finally
    //   567	574	670	finally
    //   587	589	670	finally
    //   592	594	670	finally
    //   599	606	670	finally
    //   615	617	670	finally
    //   620	622	670	finally
    //   668	670	670	finally
    //   678	687	689	finally
    //   690	692	689	finally
    //   24	33	694	finally
    //   695	697	694	finally
  }
  
  public static enum a
  {
    static
    {
      RUNNING = new a("RUNNING", 1);
      STARTING = new a("STARTING", 2);
      a locala = new a("RECEIVING", 3);
      RECEIVING = locala;
      ENUM$VALUES = new a[] { STOPPED, RUNNING, STARTING, locala };
    }
  }
}

/* Location:
 * Qualified Name:     l.c.a.a.a.s.d
 * Java Class Version: 6 (50.0)
 * JD-Core Version:    0.7.1
 */